demo_lib/__init__.py
demo_lib/hello.yaml
library_demo_jo-0.0.1.dist-info/LICENSE
library_demo_jo-0.0.1.dist-info/METADATA
library_demo_jo-0.0.1.dist-info/WHEEL
library_demo_jo-0.0.1.dist-info/top_level.txt
library_demo_jo-0.0.1.dist-info/RECORD
