Metadata-Version: 2.1
Name: library-demo-jo
Version: 0.0.1
Summary: python package demo by joneai
Author-email: joneai <mxjoneai@gmail.com>
License: MIT License
Project-URL: Homepage, https://github.com/tacnaci/library-demo-jo
Keywords: joneai,library,tutorial
Classifier: License :: OSI Approved :: MIT License
Classifier: Programming Language :: Python
Classifier: Programming Language :: Python :: 3
Requires-Python: >=3.9
License-File: LICENSE
Requires-Dist: PyYAML (>=6.0)
Provides-Extra: dev
Requires-Dist: pip-tools ; extra == 'dev'
Requires-Dist: pytest ; extra == 'dev'
